aws_cdk_connect_lib/__init__.py
aws_cdk_connect_lib/py.typed
aws_cdk_connect_lib/_jsii/__init__.py
aws_cdk_connect_lib/_jsii/aws-cdk-aws-connect-lib@0.2.1.jsii.tgz
netforbpo_aws_cdk_aws_connect_lib-0.2.1.dist-info/LICENSE
netforbpo_aws_cdk_aws_connect_lib-0.2.1.dist-info/METADATA
netforbpo_aws_cdk_aws_connect_lib-0.2.1.dist-info/WHEEL
netforbpo_aws_cdk_aws_connect_lib-0.2.1.dist-info/top_level.txt
netforbpo_aws_cdk_aws_connect_lib-0.2.1.dist-info/RECORD
