Metadata-Version: 2.1
Name: netforbpo-aws-cdk-aws-connect-lib
Version: 0.2.1
Summary: @netforbpo/aws-cdk-aws-connect-lib
Home-page: https://github.com/netforbpo/aws-cdk-aws-connect-lib.git
Author: netforbpo
License: Apache-2.0
Project-URL: Source, https://github.com/netforbpo/aws-cdk-aws-connect-lib.git
Classifier: Intended Audience :: Developers
Classifier: Operating System :: OS Independent
Classifier: Programming Language :: JavaScript
Classifier: Programming Language :: Python :: 3 :: Only
Classifier: Programming Language :: Python :: 3.9
Classifier: Programming Language :: Python :: 3.10
Classifier: Programming Language :: Python :: 3.11
Classifier: Typing :: Typed
Classifier: Development Status :: 4 - Beta
Classifier: License :: OSI Approved
Requires-Python: ~=3.9
License-File: LICENSE
Requires-Dist: aws-cdk-lib <3.0.0,>=2.233.0
Requires-Dist: constructs <11.0.0,>=10.0.5
Requires-Dist: jsii <2.0.0,>=1.122.0
Requires-Dist: publication >=0.0.3
Requires-Dist: typeguard ==2.13.3
